pyams_viewlet/__init__.py
pyams_viewlet/include.py
pyams_viewlet/interfaces.py
pyams_viewlet/manager.py
pyams_viewlet/provider.py
pyams_viewlet/viewlet.py
pyams_viewlet/doctests/README.rst
pyams_viewlet/locales/pyams_viewlet.pot
pyams_viewlet/locales/fr/LC_MESSAGES/pyams_viewlet.po
pyams_viewlet/tests/__init__.py
pyams_viewlet/tests/test_utilsdocs.py
pyams_viewlet/tests/test_utilsdocstrings.py
pyams_viewlet-2.0.1.dist-info/LICENSE
pyams_viewlet-2.0.1.dist-info/METADATA
pyams_viewlet-2.0.1.dist-info/WHEEL
pyams_viewlet-2.0.1.dist-info/namespace_packages.txt
pyams_viewlet-2.0.1.dist-info/top_level.txt
pyams_viewlet-2.0.1.dist-info/RECORD
