Metadata-Version: 2.1
Name: pyams-viewlet
Version: 2.0.1
Summary: PyAMS viewlets management package
Home-page: https://pyams.readthedocs.io
Author: Thierry Florac
Author-email: tflorac@ulthar.net
License: ZPL
Keywords: Pyramid PyAMS
Classifier: License :: OSI Approved :: Zope Public License
Classifier: Development Status :: 4 - Beta
Classifier: Programming Language :: Python
Classifier: Framework :: Pyramid
Classifier: Topic :: Software Development :: Libraries :: Python Modules
Requires-Python: >=3.7
License-File: LICENSE
Requires-Dist: setuptools
Requires-Dist: chameleon
Requires-Dist: pyams-template
Requires-Dist: pyams-utils
Requires-Dist: pyramid >=2.0.0
Requires-Dist: venusian
Requires-Dist: zope.contentprovider
Requires-Dist: zope.interface
Requires-Dist: zope.location
Provides-Extra: test
